{
  "gluon": {
    "listen": 7070,
    "dir": "./src",
    "auth": {
      "base": "token",
      "allow": [
        "/image/all",
        "/image/:image"
      ]
    },
    "publicSource": [
      "./public/build",
      "./public"
    ]
  },
  "database": {
    "dialect": "mysql",
    "host": "localhost",
    "user": "root",
    "password": "",
    "database": "sprinkler",
    "timezone": "+03:00"
  },
  "ignorePins": "true",
  "logger": {
    "level": "DEBUG"
  },
  "imageDirectory": "/home/pi/Desktop/resimler",
  "socket": "http://localhost:90"
}
